.mailmap
.pylintrc
AUTHORS
CONTRIBUTING.rst
ChangeLog
HACKING.rst
LICENSE
MANIFEST.in
Makefile
README.rst
manage.py
openstack-common.conf
requirements.txt
run_tests.sh
setup.cfg
setup.py
test-requirements.txt
tox.ini
.tx/config
doc/Makefile
doc/source/conf.py
doc/source/contributing.rst
doc/source/faq.rst
doc/source/glossary.rst
doc/source/index.rst
doc/source/intro.rst
doc/source/quickstart.rst
doc/source/testing.rst
doc/source/ref/context_processors.rst
doc/source/ref/decorators.rst
doc/source/ref/exceptions.rst
doc/source/ref/forms.rst
doc/source/ref/horizon.rst
doc/source/ref/middleware.rst
doc/source/ref/run_tests.rst
doc/source/ref/tables.rst
doc/source/ref/tabs.rst
doc/source/ref/test.rst
doc/source/ref/workflows.rst
doc/source/releases/2012_1.rst
doc/source/releases/2012_2.rst
doc/source/releases/2013_1.rst
doc/source/releases/2013_2.rst
doc/source/releases/2014_1.rst
doc/source/topics/customizing.rst
doc/source/topics/deployment.rst
doc/source/topics/policy.rst
doc/source/topics/settings.rst
doc/source/topics/tables.rst
doc/source/topics/testing.rst
doc/source/topics/tutorial.rst
doc/source/topics/workflows.rst
gbptesthorizon.egg-info/PKG-INFO
gbptesthorizon.egg-info/SOURCES.txt
gbptesthorizon.egg-info/dependency_links.txt
gbptesthorizon.egg-info/not-zip-safe
gbptesthorizon.egg-info/requires.txt
gbptesthorizon.egg-info/top_level.txt
horizon/__init__.py
horizon/base.py
horizon/context_processors.py
horizon/decorators.py
horizon/exceptions.py
horizon/loaders.py
horizon/messages.py
horizon/middleware.py
horizon/models.py
horizon/site_urls.py
horizon/version.py
horizon/views.py
horizon/browsers/__init__.py
horizon/browsers/base.py
horizon/browsers/breadcrumb.py
horizon/browsers/views.py
horizon/conf/__init__.py
horizon/conf/default.py
horizon/conf/dash_template/__init__.py
horizon/conf/dash_template/dashboard.py.tmpl
horizon/conf/dash_template/models.py
horizon/conf/dash_template/static/dash_name/css/dash_name.css
horizon/conf/dash_template/static/dash_name/js/dash_name.js
horizon/conf/dash_template/templates/dash_name/base.html
horizon/conf/panel_template/__init__.py
horizon/conf/panel_template/models.py
horizon/conf/panel_template/panel.py.tmpl
